{
 "chartType": "c",
 "blockClass": 1,
 "subjectID": "000",
 "trials": [
  {
   "data": [
    {
     "date": "1980-01-01T06:00:00.000Z",
     "value1": 1.0999999999999999,
     "value2": 0.8166666666666667
    },
    {
     "date": "1981-01-01T06:00:00.000Z",
     "value1": 7.066666666666667,
     "value2": 4.733333333333334
    },
    {
     "date": "1982-01-01T06:00:00.000Z",
     "value1": 3.7295830086804926,
     "value2": 6.075865016318858
    },
    {
     "date": "1983-01-01T06:00:00.000Z",
     "value1": 5.737758771005112,
     "value2": 4.8511270078363635
    },
    {
     "date": "1984-01-01T06:00:00.000Z",
     "value1": 0.9999999999999998,
     "value2": 2.016666666666667
    }
   ],
   "label1": "Size of the Army (millions)",
   "label2": "Military Budget (billions)",
   "ind": 2,
   "params": {
    "angle": 328,
    "actualAngle": 328.62199119571596
   },
   "opacity": 1,
   "response": 83,
   "responseTime": 1009,
   "correct": false
  },
  {
   "data": [
    {
     "date": "1980-01-01T06:00:00.000Z",
     "value1": 8.483111821115017,
     "value2": 9.427788550965488
    },
    {
     "date": "1981-01-01T06:00:00.000Z",
     "value1": 9.696900254952256,
     "value2": 8.411439324350921
    },
    {
     "date": "1982-01-01T06:00:00.000Z",
     "value1": 5.916666666666667,
     "value2": 5.637500000000001
    },
    {
     "date": "1983-01-01T06:00:00.000Z",
     "value1": 7.5,
     "value2": 1.3875
    },
    {
     "date": "1984-01-01T06:00:00.000Z",
     "value1": 7.983333333333333,
     "value2": 5.804166666666667
    }
   ],
   "label1": "China's Growth (%)",
   "label2": "Japan's Growth (%)",
   "ind": 0,
   "params": {
    "angle": 320,
    "actualAngle": 320.0593361160718
   },
   "opacity": 1,
   "response": 83,
   "responseTime": 810,
   "correct": false
  },
  {
   "data": [
    {
     "date": "1980-01-01T06:00:00.000Z",
     "value1": 1.9666666666666668,
     "value2": 6.316666666666667
    },
    {
     "date": "1981-01-01T06:00:00.000Z",
     "value1": 3.3,
     "value2": 3.433333333333334
    },
    {
     "date": "1982-01-01T06:00:00.000Z",
     "value1": 4.183187249582261,
     "value2": 0.21468440608587103
    },
    {
     "date": "1983-01-01T06:00:00.000Z",
     "value1": 8.207938825758173,
     "value2": 4.176441669254563
    },
    {
     "date": "1984-01-01T06:00:00.000Z",
     "value1": 7.916666666666667,
     "value2": 8.216666666666669
    }
   ],
   "label1": "China's Growth (%)",
   "label2": "Japan's Growth (%)",
   "ind": 2,
   "params": {
    "slope1": 4,
    "slope2": 4,
    "actualSlope1": 4.024751576175913,
    "actualSlope2": 3.961757263168692,
    "dist": 4
   },
   "opacity": 1,
   "response": 83,
   "responseTime": 584,
   "correct": true
  },
  {
   "data": [
    {
     "date": "1980-01-01T06:00:00.000Z",
     "value1": 6.066719603259116,
     "value2": 2.236713287420571
    },
    {
     "date": "1981-01-01T06:00:00.000Z",
     "value1": 6.13571831035744,
     "value2": 2.739465240523381
    },
    {
     "date": "1982-01-01T06:00:00.000Z",
     "value1": 2.5833333333333335,
     "value2": 3.6208333333333336
    },
    {
     "date": "1983-01-01T06:00:00.000Z",
     "value1": 2.2,
     "value2": 4.687500000000001
    },
    {
     "date": "1984-01-01T06:00:00.000Z",
     "value1": 1.9666666666666668,
     "value2": 8.004166666666666
    }
   ],
   "label1": "Size of the Army (millions)",
   "label2": "Military Budget (billions)",
   "ind": 0,
   "params": {
    "angle": 82,
    "actualAngle": 82.18542937934399
   },
   "opacity": 1,
   "response": 83,
   "responseTime": 667,
   "correct": true
  },
  {
   "data": [
    {
     "date": "1980-01-01T06:00:00.000Z",
     "value1": 6.930012600496411,
     "value2": 3.361439408245497
    },
    {
     "date": "1981-01-01T06:00:00.000Z",
     "value1": 9.886684443522245,
     "value2": 3.45525763577316
    },
    {
     "date": "1982-01-01T06:00:00.000Z",
     "value1": 5.866666666666667,
     "value2": 6.833333333333333
    },
    {
     "date": "1983-01-01T06:00:00.000Z",
     "value1": 4.916666666666667,
     "value2": 3.433333333333334
    },
    {
     "date": "1984-01-01T06:00:00.000Z",
     "value1": 3.2,
     "value2": 1.0666666666666667
    }
   ],
   "label1": "Price of Gold (x100)",
   "label2": "Dow-Jones Industrial Index (x1000)",
   "ind": 0,
   "params": {
    "slope1": 3,
    "slope2": 0,
    "actualSlope1": 2.956671843025833,
    "actualSlope2": 0.09381822752766311,
    "dist": 5
   },
   "opacity": 1,
   "response": 83,
   "responseTime": 473,
   "correct": true
  },
  {
   "data": [
    {
     "date": "1980-01-01T06:00:00.000Z",
     "value1": 1.2333333333333334,
     "value2": 3.7833333333333337
    },
    {
     "date": "1981-01-01T06:00:00.000Z",
     "value1": 4.91341910790652,
     "value2": 2.42029370944947
    },
    {
     "date": "1982-01-01T06:00:00.000Z",
     "value1": 6.846785780414939,
     "value2": 1.339911178871989
    },
    {
     "date": "1983-01-01T06:00:00.000Z",
     "value1": 1.9166666666666667,
     "value2": 6.116666666666667
    },
    {
     "date": "1984-01-01T06:00:00.000Z",
     "value1": 1.1333333333333333,
     "value2": 4.166666666666667
    }
   ],
   "label1": "Miles driven per capita each year (thousands)",
   "label2": "Price of a gallon of gas (US$)",
   "ind": 1,
   "params": {
    "slope1": 2,
    "slope2": -1,
    "actualSlope1": 1.9333666725084186,
    "actualSlope2": -1.0803825305774808,
    "dist": 4
   },
   "opacity": 1,
   "response": 83,
   "responseTime": 473,
   "correct": false
  },
  {
   "data": [
    {
     "date": "1980-01-01T06:00:00.000Z",
     "value1": 7.826435179449618,
     "value2": 2.871225125784986
    },
    {
     "date": "1981-01-01T06:00:00.000Z",
     "value1": 7.91784290582873,
     "value2": 6.873052959493362
    },
    {
     "date": "1982-01-01T06:00:00.000Z",
     "value1": 5.033333333333334,
     "value2": 6.483333333333334
    },
    {
     "date": "1983-01-01T06:00:00.000Z",
     "value1": 4.816666666666667,
     "value2": 4.733333333333334
    },
    {
     "date": "1984-01-01T06:00:00.000Z",
     "value1": 7.266666666666667,
     "value2": 3.5500000000000003
    }
   ],
   "label1": "Vehicle miles driven per capita (thousands)",
   "label2": "Auto fatalities per 1,000 people",
   "ind": 0,
   "params": {
    "slope1": 0,
    "slope2": 4,
    "actualSlope1": 0.0914077263791114,
    "actualSlope2": 4.001827833708376,
    "dist": 3
   },
   "opacity": 1,
   "response": 83,
   "responseTime": 379,
   "correct": true
  },
  {
   "data": [
    {
     "date": "1980-01-01T06:00:00.000Z",
     "value1": 2.475570379756391,
     "value2": 4.5770204439759254
    },
    {
     "date": "1981-01-01T06:00:00.000Z",
     "value1": 0.5591444595156567,
     "value2": 5.025550237273228
    },
    {
     "date": "1982-01-01T06:00:00.000Z",
     "value1": 7.616666666666667,
     "value2": 5.700000000000001
    },
    {
     "date": "1983-01-01T06:00:00.000Z",
     "value1": 4.15,
     "value2": 6.033333333333334
    },
    {
     "date": "1984-01-01T06:00:00.000Z",
     "value1": 8.866666666666667,
     "value2": 3.75
    }
   ],
   "label1": "Production of refined helium worldwide (billion cubic feet)",
   "label2": "Price per thousand cubic feet of refined helium",
   "ind": 0,
   "params": {
    "angle": 166,
    "actualAngle": 166.82731681736186
   },
   "opacity": 1,
   "response": 83,
   "responseTime": 417,
   "correct": false
  },
  {
   "data": [
    {
     "date": "1980-01-01T06:00:00.000Z",
     "value1": 7.416666666666667,
     "value2": 7.754166666666668
    },
    {
     "date": "1981-01-01T06:00:00.000Z",
     "value1": 2.2333333333333334,
     "value2": 6.470833333333333
    },
    {
     "date": "1982-01-01T06:00:00.000Z",
     "value1": 5.916666666666667,
     "value2": 5.637500000000001
    },
    {
     "date": "1983-01-01T06:00:00.000Z",
     "value1": 9.88877136958763,
     "value2": 1.9527828935068101
    },
    {
     "date": "1984-01-01T06:00:00.000Z",
     "value1": 5.979976848466322,
     "value2": 3.915965324547142
    }
   ],
   "label1": "China's Growth (%)",
   "label2": "Japan's Growth (%)",
   "ind": 3,
   "params": {
    "slope1": -4,
    "slope2": 2,
    "actualSlope1": -3.908794521121308,
    "actualSlope2": 1.9631824310403316,
    "dist": 5
   },
   "opacity": 1,
   "response": 83,
   "responseTime": 432,
   "correct": false
  },
  {
   "data": [
    {
     "date": "1980-01-01T06:00:00.000Z",
     "value1": 6.783333333333333,
     "value2": 2.4208333333333334
    },
    {
     "date": "1981-01-01T06:00:00.000Z",
     "value1": 6.684998674318194,
     "value2": 3.7095122803933918
    },
    {
     "date": "1982-01-01T06:00:00.000Z",
     "value1": 3.730561745259911,
     "value2": 2.706048139184713
    },
    {
     "date": "1983-01-01T06:00:00.000Z",
     "value1": 2.2,
     "value2": 4.687500000000001
    },
    {
     "date": "1984-01-01T06:00:00.000Z",
     "value1": 1.9666666666666668,
     "value2": 8.004166666666666
    }
   ],
   "label1": "Size of the Army (millions)",
   "label2": "Military Budget (billions)",
   "ind": 1,
   "params": {
    "slope1": -3,
    "slope2": -1,
    "actualSlope1": -2.9544369290582835,
    "actualSlope2": -1.0034641412086784,
    "dist": 2
   },
   "opacity": 1,
   "response": 83,
   "responseTime": 501,
   "correct": true
  }
 ],
 "avgRT": 574.5,
 "avgCorrect": 0.5
}